ldtk/__init__.py
ldtk/pyglet_ldtk_loader.py
pyglet_ldtk-0.1.2.dist-info/licenses/LICENSE
pyglet_ldtk-0.1.2.dist-info/METADATA
pyglet_ldtk-0.1.2.dist-info/WHEEL
pyglet_ldtk-0.1.2.dist-info/top_level.txt
pyglet_ldtk-0.1.2.dist-info/RECORD
