Metadata-Version: 2.4
Name: pyglet-ldtk
Version: 0.1.2
Summary: A loader for LDtk (Level Designer Toolkit) maps, specifically designed for use with the pyglet game development library.
Author-email: Dania Rifki <atomicnumberphi@gmail.com>
License: MIT
Project-URL: Homepage, https://github.com/Kaleidosium/pyglet-ldtk
Classifier: License :: OSI Approved :: MIT License
Classifier: Programming Language :: Python :: 3
Classifier: Programming Language :: Python :: 3.10
Classifier: Programming Language :: Python :: 3.11
Classifier: Programming Language :: Python :: 3.12
Classifier: Programming Language :: Python :: 3.13
Classifier: Programming Language :: Python :: 3.14
Requires-Python: >=3.10
License-File: LICENSE
Requires-Dist: pyglet>=2.1.11
Dynamic: license-file
